{
  "variation": "1",
  "element_pattern": {
    "A[1,1]1:1": {
      "file_name": "exportfield_0.ffd",
      "location": [
        "-0.037022",
        "-0.027767",
        "0.000000"
      ],
      "incident_power": {
        "30000000000.0": 1.0,
        "31000000000.0": 1.0,
        "32000000000.0": 1.0
      },
      "radiated_power": {
        "30000000000.0": 1.013379,
        "31000000000.0": 1.014579,
        "32000000000.0": 1.013644
      },
      "accepted_power": {
        "30000000000.0": 0.997132,
        "31000000000.0": 0.999411,
        "32000000000.0": 0.996094
      }
    },
    "A[1,1]1:2": {
      "file_name": "exportfield_1.ffd",
      "location": [
        "-0.037022",
        "-0.027767",
        "0.000000"
      ],
      "incident_power": {
        "30000000000.0": 1.0,
        "31000000000.0": 1.0,
        "32000000000.0": 1.0
      },
      "radiated_power": {
        "30000000000.0": 1.012735,
        "31000000000.0": 1.013531,
        "32000000000.0": 1.013229
      },
      "accepted_power": {
        "30000000000.0": 0.996923,
        "31000000000.0": 0.999195,
        "32000000000.0": 0.996127
      }
    },
    "A[1,2]1:1": {
      "file_name": "exportfield_2.ffd",
      "location": [
        "-0.018511",
        "-0.027767",
        "0.000000"
      ],
      "incident_power": {
        "30000000000.0": 1.0,
        "31000000000.0": 1.0,
        "32000000000.0": 1.0
      },
      "radiated_power": {
        "30000000000.0": 1.010374,
        "31000000000.0": 1.010005,
        "32000000000.0": 1.008293
      },
      "accepted_power": {
        "30000000000.0": 0.997143,
        "31000000000.0": 0.999405,
        "32000000000.0": 0.995945
      }
    },
    "A[1,2]1:2": {
      "file_name": "exportfield_3.ffd",
      "location": [
        "-0.018511",
        "-0.027767",
        "0.000000"
      ],
      "incident_power": {
        "30000000000.0": 1.0,
        "31000000000.0": 1.0,
        "32000000000.0": 1.0
      },
      "radiated_power": {
        "30000000000.0": 1.010082,
        "31000000000.0": 1.009501,
        "32000000000.0": 1.009769
      },
      "accepted_power": {
        "30000000000.0": 0.996882,
        "31000000000.0": 0.999169,
        "32000000000.0": 0.996146
      }
    },
    "A[1,3]1:1": {
      "file_name": "exportfield_4.ffd",
      "location": [
        "-0.000000",
        "-0.027767",
        "0.000000"
      ],
      "incident_power": {
        "30000000000.0": 1.0,
        "31000000000.0": 1.0,
        "32000000000.0": 1.0
      },
      "radiated_power": {
        "30000000000.0": 1.014617,
        "31000000000.0": 1.014409,
        "32000000000.0": 1.012775
      },
      "accepted_power": {
        "30000000000.0": 0.997137,
        "31000000000.0": 0.999401,
        "32000000000.0": 0.995961
      }
    },
    "A[1,3]1:2": {
      "file_name": "exportfield_5.ffd",
      "location": [
        "-0.000000",
        "-0.027767",
        "0.000000"
      ],
      "incident_power": {
        "30000000000.0": 1.0,
        "31000000000.0": 1.0,
        "32000000000.0": 1.0
      },
      "radiated_power": {
        "30000000000.0": 1.013636,
        "31000000000.0": 1.013788,
        "32000000000.0": 1.01299
      },
      "accepted_power": {
        "30000000000.0": 0.99688,
        "31000000000.0": 0.999174,
        "32000000000.0": 0.996145
      }
    },
    "A[1,4]1:1": {
      "file_name": "exportfield_6.ffd",
      "location": [
        "0.018511",
        "-0.027767",
        "0.000000"
      ],
      "incident_power": {
        "30000000000.0": 1.0,
        "31000000000.0": 1.0,
        "32000000000.0": 1.0
      },
      "radiated_power": {
        "30000000000.0": 1.013312,
        "31000000000.0": 1.013296,
        "32000000000.0": 1.011193
      },
      "accepted_power": {
        "30000000000.0": 0.99714,
        "31000000000.0": 0.999402,
        "32000000000.0": 0.995964
      }
    },
    "A[1,4]1:2": {
      "file_name": "exportfield_7.ffd",
      "location": [
        "0.018511",
        "-0.027767",
        "0.000000"
      ],
      "incident_power": {
        "30000000000.0": 1.0,
        "31000000000.0": 1.0,
        "32000000000.0": 1.0
      },
      "radiated_power": {
        "30000000000.0": 1.012604,
        "31000000000.0": 1.012414,
        "32000000000.0": 1.011253
      },
      "accepted_power": {
        "30000000000.0": 0.99688,
        "31000000000.0": 0.999172,
        "32000000000.0": 0.996144
      }
    },
    "A[1,5]1:1": {
      "file_name": "exportfield_8.ffd",
      "location": [
        "0.037022",
        "-0.027767",
        "0.000000"
      ],
      "incident_power": {
        "30000000000.0": 1.0,
        "31000000000.0": 1.0,
        "32000000000.0": 1.0
      },
      "radiated_power": {
        "30000000000.0": 1.012936,
        "31000000000.0": 1.01383,
        "32000000000.0": 1.012444
      },
      "accepted_power": {
        "30000000000.0": 0.99714,
        "31000000000.0": 0.999417,
        "32000000000.0": 0.996101
      }
    },
    "A[1,5]1:2": {
      "file_name": "exportfield_9.ffd",
      "location": [
        "0.037022",
        "-0.027767",
        "0.000000"
      ],
      "incident_power": {
        "30000000000.0": 1.0,
        "31000000000.0": 1.0,
        "32000000000.0": 1.0
      },
      "radiated_power": {
        "30000000000.0": 1.012349,
        "31000000000.0": 1.01213,
        "32000000000.0": 1.011919
      },
      "accepted_power": {
        "30000000000.0": 0.996921,
        "31000000000.0": 0.999192,
        "32000000000.0": 0.996113
      }
    },
    "A[2,1]1:1": {
      "file_name": "exportfield_10.ffd",
      "location": [
        "-0.037022",
        "-0.009256",
        "0.000000"
      ],
      "incident_power": {
        "30000000000.0": 1.0,
        "31000000000.0": 1.0,
        "32000000000.0": 1.0
      },
      "radiated_power": {
        "30000000000.0": 1.014806,
        "31000000000.0": 1.014957,
        "32000000000.0": 1.014552
      },
      "accepted_power": {
        "30000000000.0": 0.997092,
        "31000000000.0": 0.999394,
        "32000000000.0": 0.996121
      }
    },
    "A[2,1]1:2": {
      "file_name": "exportfield_11.ffd",
      "location": [
        "-0.037022",
        "-0.009256",
        "0.000000"
      ],
      "incident_power": {
        "30000000000.0": 1.0,
        "31000000000.0": 1.0,
        "32000000000.0": 1.0
      },
      "radiated_power": {
        "30000000000.0": 1.013549,
        "31000000000.0": 1.01263,
        "32000000000.0": 1.011383
      },
      "accepted_power": {
        "30000000000.0": 0.996926,
        "31000000000.0": 0.999185,
        "32000000000.0": 0.995972
      }
    },
    "A[2,2]1:1": {
      "file_name": "exportfield_12.ffd",
      "location": [
        "-0.018511",
        "-0.009256",
        "0.000000"
      ],
      "incident_power": {
        "30000000000.0": 1.0,
        "31000000000.0": 1.0,
        "32000000000.0": 1.0
      },
      "radiated_power": {
        "30000000000.0": 1.009805,
        "31000000000.0": 1.01045,
        "32000000000.0": 1.007403
      },
      "accepted_power": {
        "30000000000.0": 0.997098,
        "31000000000.0": 0.999382,
        "32000000000.0": 0.995987
      }
    },
    "A[2,2]1:2": {
      "file_name": "exportfield_13.ffd",
      "location": [
        "-0.018511",
        "-0.009256",
        "0.000000"
      ],
      "incident_power": {
        "30000000000.0": 1.0,
        "31000000000.0": 1.0,
        "32000000000.0": 1.0
      },
      "radiated_power": {
        "30000000000.0": 1.010043,
        "31000000000.0": 1.009313,
        "32000000000.0": 1.007197
      },
      "accepted_power": {
        "30000000000.0": 0.99688,
        "31000000000.0": 0.999161,
        "32000000000.0": 0.996015
      }
    },
    "A[2,3]1:1": {
      "file_name": "exportfield_14.ffd",
      "location": [
        "-0.000000",
        "-0.009256",
        "0.000000"
      ],
      "incident_power": {
        "30000000000.0": 1.0,
        "31000000000.0": 1.0,
        "32000000000.0": 1.0
      },
      "radiated_power": {
        "30000000000.0": 1.011274,
        "31000000000.0": 1.010318,
        "32000000000.0": 1.007956
      },
      "accepted_power": {
        "30000000000.0": 0.997098,
        "31000000000.0": 0.999382,
        "32000000000.0": 0.995987
      }
    },
    "A[2,3]1:2": {
      "file_name": "exportfield_15.ffd",
      "location": [
        "-0.000000",
        "-0.009256",
        "0.000000"
      ],
      "incident_power": {
        "30000000000.0": 1.0,
        "31000000000.0": 1.0,
        "32000000000.0": 1.0
      },
      "radiated_power": {
        "30000000000.0": 1.011254,
        "31000000000.0": 1.010309,
        "32000000000.0": 1.008119
      },
      "accepted_power": {
        "30000000000.0": 0.996879,
        "31000000000.0": 0.999156,
        "32000000000.0": 0.996003
      }
    },
    "A[2,4]1:1": {
      "file_name": "exportfield_16.ffd",
      "location": [
        "0.018511",
        "-0.009256",
        "0.000000"
      ],
      "incident_power": {
        "30000000000.0": 1.0,
        "31000000000.0": 1.0,
        "32000000000.0": 1.0
      },
      "radiated_power": {
        "30000000000.0": 1.013414,
        "31000000000.0": 1.013219,
        "32000000000.0": 1.010534
      },
      "accepted_power": {
        "30000000000.0": 0.997099,
        "31000000000.0": 0.999387,
        "32000000000.0": 0.995987
      }
    },
    "A[2,4]1:2": {
      "file_name": "exportfield_17.ffd",
      "location": [
        "0.018511",
        "-0.009256",
        "0.000000"
      ],
      "incident_power": {
        "30000000000.0": 1.0,
        "31000000000.0": 1.0,
        "32000000000.0": 1.0
      },
      "radiated_power": {
        "30000000000.0": 1.013345,
        "31000000000.0": 1.012357,
        "32000000000.0": 1.010541
      },
      "accepted_power": {
        "30000000000.0": 0.99688,
        "31000000000.0": 0.999161,
        "32000000000.0": 0.996009
      }
    },
    "A[2,5]1:1": {
      "file_name": "exportfield_18.ffd",
      "location": [
        "0.037022",
        "-0.009256",
        "0.000000"
      ],
      "incident_power": {
        "30000000000.0": 1.0,
        "31000000000.0": 1.0,
        "32000000000.0": 1.0
      },
      "radiated_power": {
        "30000000000.0": 1.013026,
        "31000000000.0": 1.014265,
        "32000000000.0": 1.013229
      },
      "accepted_power": {
        "30000000000.0": 0.997096,
        "31000000000.0": 0.999396,
        "32000000000.0": 0.99612
      }
    },
    "A[2,5]1:2": {
      "file_name": "exportfield_19.ffd",
      "location": [
        "0.037022",
        "-0.009256",
        "0.000000"
      ],
      "incident_power": {
        "30000000000.0": 1.0,
        "31000000000.0": 1.0,
        "32000000000.0": 1.0
      },
      "radiated_power": {
        "30000000000.0": 1.012737,
        "31000000000.0": 1.012799,
        "32000000000.0": 1.011119
      },
      "accepted_power": {
        "30000000000.0": 0.996928,
        "31000000000.0": 0.999184,
        "32000000000.0": 0.995969
      }
    },
    "A[3,1]1:1": {
      "file_name": "exportfield_20.ffd",
      "location": [
        "-0.037022",
        "0.009256",
        "0.000000"
      ],
      "incident_power": {
        "30000000000.0": 1.0,
        "31000000000.0": 1.0,
        "32000000000.0": 1.0
      },
      "radiated_power": {
        "30000000000.0": 1.013743,
        "31000000000.0": 1.014102,
        "32000000000.0": 1.013223
      },
      "accepted_power": {
        "30000000000.0": 0.997095,
        "31000000000.0": 0.999395,
        "32000000000.0": 0.996127
      }
    },
    "A[3,1]1:2": {
      "file_name": "exportfield_21.ffd",
      "location": [
        "-0.037022",
        "0.009256",
        "0.000000"
      ],
      "incident_power": {
        "30000000000.0": 1.0,
        "31000000000.0": 1.0,
        "32000000000.0": 1.0
      },
      "radiated_power": {
        "30000000000.0": 1.01448,
        "31000000000.0": 1.014009,
        "32000000000.0": 1.012254
      },
      "accepted_power": {
        "30000000000.0": 0.996921,
        "31000000000.0": 0.999178,
        "32000000000.0": 0.995972
      }
    },
    "A[3,2]1:1": {
      "file_name": "exportfield_22.ffd",
      "location": [
        "-0.018511",
        "0.009256",
        "0.000000"
      ],
      "incident_power": {
        "30000000000.0": 1.0,
        "31000000000.0": 1.0,
        "32000000000.0": 1.0
      },
      "radiated_power": {
        "30000000000.0": 1.009692,
        "31000000000.0": 1.008736,
        "32000000000.0": 1.006109
      },
      "accepted_power": {
        "30000000000.0": 0.997101,
        "31000000000.0": 0.999385,
        "32000000000.0": 0.995979
      }
    },
    "A[3,2]1:2": {
      "file_name": "exportfield_23.ffd",
      "location": [
        "-0.018511",
        "0.009256",
        "0.000000"
      ],
      "incident_power": {
        "30000000000.0": 1.0,
        "31000000000.0": 1.0,
        "32000000000.0": 1.0
      },
      "radiated_power": {
        "30000000000.0": 1.009128,
        "31000000000.0": 1.007985,
        "32000000000.0": 1.005612
      },
      "accepted_power": {
        "30000000000.0": 0.99688,
        "31000000000.0": 0.999159,
        "32000000000.0": 0.996011
      }
    },
    "A[3,3]1:1": {
      "file_name": "exportfield_24.ffd",
      "location": [
        "-0.000000",
        "0.009256",
        "0.000000"
      ],
      "incident_power": {
        "30000000000.0": 1.0,
        "31000000000.0": 1.0,
        "32000000000.0": 1.0
      },
      "radiated_power": {
        "30000000000.0": 1.013627,
        "31000000000.0": 1.012655,
        "32000000000.0": 1.0103
      },
      "accepted_power": {
        "30000000000.0": 0.997098,
        "31000000000.0": 0.999383,
        "32000000000.0": 0.995988
      }
    },
    "A[3,3]1:2": {
      "file_name": "exportfield_25.ffd",
      "location": [
        "-0.000000",
        "0.009256",
        "0.000000"
      ],
      "incident_power": {
        "30000000000.0": 1.0,
        "31000000000.0": 1.0,
        "32000000000.0": 1.0
      },
      "radiated_power": {
        "30000000000.0": 1.012003,
        "31000000000.0": 1.011482,
        "32000000000.0": 1.008837
      },
      "accepted_power": {
        "30000000000.0": 0.996879,
        "31000000000.0": 0.99916,
        "32000000000.0": 0.996007
      }
    },
    "A[3,4]1:1": {
      "file_name": "exportfield_26.ffd",
      "location": [
        "0.018511",
        "0.009256",
        "0.000000"
      ],
      "incident_power": {
        "30000000000.0": 1.0,
        "31000000000.0": 1.0,
        "32000000000.0": 1.0
      },
      "radiated_power": {
        "30000000000.0": 1.013287,
        "31000000000.0": 1.01241,
        "32000000000.0": 1.009395
      },
      "accepted_power": {
        "30000000000.0": 0.997094,
        "31000000000.0": 0.999382,
        "32000000000.0": 0.995987
      }
    },
    "A[3,4]1:2": {
      "file_name": "exportfield_27.ffd",
      "location": [
        "0.018511",
        "0.009256",
        "0.000000"
      ],
      "incident_power": {
        "30000000000.0": 1.0,
        "31000000000.0": 1.0,
        "32000000000.0": 1.0
      },
      "radiated_power": {
        "30000000000.0": 1.014277,
        "31000000000.0": 1.012865,
        "32000000000.0": 1.01053
      },
      "accepted_power": {
        "30000000000.0": 0.996877,
        "31000000000.0": 0.999156,
        "32000000000.0": 0.996011
      }
    },
    "A[3,5]1:1": {
      "file_name": "exportfield_28.ffd",
      "location": [
        "0.037022",
        "0.009256",
        "0.000000"
      ],
      "incident_power": {
        "30000000000.0": 1.0,
        "31000000000.0": 1.0,
        "32000000000.0": 1.0
      },
      "radiated_power": {
        "30000000000.0": 1.01443,
        "31000000000.0": 1.015076,
        "32000000000.0": 1.013229
      },
      "accepted_power": {
        "30000000000.0": 0.997096,
        "31000000000.0": 0.999394,
        "32000000000.0": 0.996122
      }
    },
    "A[3,5]1:2": {
      "file_name": "exportfield_29.ffd",
      "location": [
        "0.037022",
        "0.009256",
        "0.000000"
      ],
      "incident_power": {
        "30000000000.0": 1.0,
        "31000000000.0": 1.0,
        "32000000000.0": 1.0
      },
      "radiated_power": {
        "30000000000.0": 1.014259,
        "31000000000.0": 1.013497,
        "32000000000.0": 1.011554
      },
      "accepted_power": {
        "30000000000.0": 0.996924,
        "31000000000.0": 0.999179,
        "32000000000.0": 0.995972
      }
    },
    "A[4,1]1:1": {
      "file_name": "exportfield_30.ffd",
      "location": [
        "-0.037022",
        "0.027767",
        "0.000000"
      ],
      "incident_power": {
        "30000000000.0": 1.0,
        "31000000000.0": 1.0,
        "32000000000.0": 1.0
      },
      "radiated_power": {
        "30000000000.0": 1.01527,
        "31000000000.0": 1.014432,
        "32000000000.0": 1.014521
      },
      "accepted_power": {
        "30000000000.0": 0.997138,
        "31000000000.0": 0.999408,
        "32000000000.0": 0.996076
      }
    },
    "A[4,1]1:2": {
      "file_name": "exportfield_31.ffd",
      "location": [
        "-0.037022",
        "0.027767",
        "0.000000"
      ],
      "incident_power": {
        "30000000000.0": 1.0,
        "31000000000.0": 1.0,
        "32000000000.0": 1.0
      },
      "radiated_power": {
        "30000000000.0": 1.014397,
        "31000000000.0": 1.014739,
        "32000000000.0": 1.013456
      },
      "accepted_power": {
        "30000000000.0": 0.996924,
        "31000000000.0": 0.999188,
        "32000000000.0": 0.996101
      }
    },
    "A[4,2]1:1": {
      "file_name": "exportfield_32.ffd",
      "location": [
        "-0.018511",
        "0.027767",
        "0.000000"
      ],
      "incident_power": {
        "30000000000.0": 1.0,
        "31000000000.0": 1.0,
        "32000000000.0": 1.0
      },
      "radiated_power": {
        "30000000000.0": 1.014131,
        "31000000000.0": 1.013907,
        "32000000000.0": 1.011118
      },
      "accepted_power": {
        "30000000000.0": 0.997148,
        "31000000000.0": 0.999403,
        "32000000000.0": 0.995949
      }
    },
    "A[4,2]1:2": {
      "file_name": "exportfield_33.ffd",
      "location": [
        "-0.018511",
        "0.027767",
        "0.000000"
      ],
      "incident_power": {
        "30000000000.0": 1.0,
        "31000000000.0": 1.0,
        "32000000000.0": 1.0
      },
      "radiated_power": {
        "30000000000.0": 1.013774,
        "31000000000.0": 1.014214,
        "32000000000.0": 1.013409
      },
      "accepted_power": {
        "30000000000.0": 0.996885,
        "31000000000.0": 0.999163,
        "32000000000.0": 0.996147
      }
    },
    "A[4,3]1:1": {
      "file_name": "exportfield_34.ffd",
      "location": [
        "-0.000000",
        "0.027767",
        "0.000000"
      ],
      "incident_power": {
        "30000000000.0": 1.0,
        "31000000000.0": 1.0,
        "32000000000.0": 1.0
      },
      "radiated_power": {
        "30000000000.0": 1.012656,
        "31000000000.0": 1.012868,
        "32000000000.0": 1.010265
      },
      "accepted_power": {
        "30000000000.0": 0.997146,
        "31000000000.0": 0.999407,
        "32000000000.0": 0.995944
      }
    },
    "A[4,3]1:2": {
      "file_name": "exportfield_35.ffd",
      "location": [
        "-0.000000",
        "0.027767",
        "0.000000"
      ],
      "incident_power": {
        "30000000000.0": 1.0,
        "31000000000.0": 1.0,
        "32000000000.0": 1.0
      },
      "radiated_power": {
        "30000000000.0": 1.012427,
        "31000000000.0": 1.012567,
        "32000000000.0": 1.011343
      },
      "accepted_power": {
        "30000000000.0": 0.996883,
        "31000000000.0": 0.999163,
        "32000000000.0": 0.996152
      }
    },
    "A[4,4]1:1": {
      "file_name": "exportfield_36.ffd",
      "location": [
        "0.018511",
        "0.027767",
        "0.000000"
      ],
      "incident_power": {
        "30000000000.0": 1.0,
        "31000000000.0": 1.0,
        "32000000000.0": 1.0
      },
      "radiated_power": {
        "30000000000.0": 1.013276,
        "31000000000.0": 1.013164,
        "32000000000.0": 1.010793
      },
      "accepted_power": {
        "30000000000.0": 0.997146,
        "31000000000.0": 0.999403,
        "32000000000.0": 0.995943
      }
    },
    "A[4,4]1:2": {
      "file_name": "exportfield_37.ffd",
      "location": [
        "0.018511",
        "0.027767",
        "0.000000"
      ],
      "incident_power": {
        "30000000000.0": 1.0,
        "31000000000.0": 1.0,
        "32000000000.0": 1.0
      },
      "radiated_power": {
        "30000000000.0": 1.013743,
        "31000000000.0": 1.013949,
        "32000000000.0": 1.012548
      },
      "accepted_power": {
        "30000000000.0": 0.996884,
        "31000000000.0": 0.999162,
        "32000000000.0": 0.996141
      }
    },
    "A[4,5]1:1": {
      "file_name": "exportfield_38.ffd",
      "location": [
        "0.037022",
        "0.027767",
        "0.000000"
      ],
      "incident_power": {
        "30000000000.0": 1.0,
        "31000000000.0": 1.0,
        "32000000000.0": 1.0
      },
      "radiated_power": {
        "30000000000.0": 1.014689,
        "31000000000.0": 1.015164,
        "32000000000.0": 1.013834
      },
      "accepted_power": {
        "30000000000.0": 0.997143,
        "31000000000.0": 0.999413,
        "32000000000.0": 0.996087
      }
    },
    "A[4,5]1:2": {
      "file_name": "exportfield_39.ffd",
      "location": [
        "0.037022",
        "0.027767",
        "0.000000"
      ],
      "incident_power": {
        "30000000000.0": 1.0,
        "31000000000.0": 1.0,
        "32000000000.0": 1.0
      },
      "radiated_power": {
        "30000000000.0": 1.014927,
        "31000000000.0": 1.014666,
        "32000000000.0": 1.013996
      },
      "accepted_power": {
        "30000000000.0": 0.996928,
        "31000000000.0": 0.999182,
        "32000000000.0": 0.996116
      }
    }
  },
  "touchstone_file": "Sweep_DV8806.s40p",
  "model_info": {
    "WA_metal": [
      "geometry\\WA_metal.obj",
      [
        128,
        128,
        255
      ],
      0.19999999999999996,
      "mm"
    ],
    "Cap": [
      "geometry\\Cap.obj",
      [
        143,
        175,
        143
      ],
      0.4,
      "mm"
    ]
  },
  "component_objects": {
    "Horn_ffd2_1": [
      [
        -0.03702236994661336,
        -0.027766777459960004,
        0.019966177702799986
      ],
      "WA_metal",
      "Cap",
      "WA_vacuum1",
      "Region1"
    ]
  },
  "cell_position": [
    [
      [
        "Horn_ffd2_1",
        [
          0.0,
          0.0,
          0.0
        ],
        0,
        [
          1,
          1
        ]
      ],
      [
        "Horn_ffd2_1",
        [
          0.018511184973306703,
          0.0,
          0.0
        ],
        0,
        [
          1,
          2
        ]
      ],
      [
        "Horn_ffd2_1",
        [
          0.037022369946613405,
          0.0,
          0.0
        ],
        0,
        [
          1,
          3
        ]
      ],
      [
        "Horn_ffd2_1",
        [
          0.05553355491992011,
          0.0,
          0.0
        ],
        0,
        [
          1,
          4
        ]
      ],
      [
        "Horn_ffd2_1",
        [
          0.07404473989322681,
          0.0,
          0.0
        ],
        0,
        [
          1,
          5
        ]
      ]
    ],
    [
      [
        "Horn_ffd2_1",
        [
          0.0,
          0.018511184973306703,
          0.0
        ],
        0,
        [
          2,
          1
        ]
      ],
      [
        "Horn_ffd2_1",
        [
          0.018511184973306703,
          0.018511184973306703,
          0.0
        ],
        0,
        [
          2,
          2
        ]
      ],
      [
        "Horn_ffd2_1",
        [
          0.037022369946613405,
          0.018511184973306703,
          0.0
        ],
        0,
        [
          2,
          3
        ]
      ],
      [
        "Horn_ffd2_1",
        [
          0.05553355491992011,
          0.018511184973306703,
          0.0
        ],
        0,
        [
          2,
          4
        ]
      ],
      [
        "Horn_ffd2_1",
        [
          0.07404473989322681,
          0.018511184973306703,
          0.0
        ],
        0,
        [
          2,
          5
        ]
      ]
    ],
    [
      [
        "Horn_ffd2_1",
        [
          0.0,
          0.037022369946613405,
          0.0
        ],
        0,
        [
          3,
          1
        ]
      ],
      [
        "Horn_ffd2_1",
        [
          0.018511184973306703,
          0.037022369946613405,
          0.0
        ],
        0,
        [
          3,
          2
        ]
      ],
      [
        "Horn_ffd2_1",
        [
          0.037022369946613405,
          0.037022369946613405,
          0.0
        ],
        0,
        [
          3,
          3
        ]
      ],
      [
        "Horn_ffd2_1",
        [
          0.05553355491992011,
          0.037022369946613405,
          0.0
        ],
        0,
        [
          3,
          4
        ]
      ],
      [
        "Horn_ffd2_1",
        [
          0.07404473989322681,
          0.037022369946613405,
          0.0
        ],
        0,
        [
          3,
          5
        ]
      ]
    ],
    [
      [
        "Horn_ffd2_1",
        [
          0.0,
          0.05553355491992011,
          0.0
        ],
        0,
        [
          4,
          1
        ]
      ],
      [
        "Horn_ffd2_1",
        [
          0.018511184973306703,
          0.05553355491992011,
          0.0
        ],
        0,
        [
          4,
          2
        ]
      ],
      [
        "Horn_ffd2_1",
        [
          0.037022369946613405,
          0.05553355491992011,
          0.0
        ],
        0,
        [
          4,
          3
        ]
      ],
      [
        "Horn_ffd2_1",
        [
          0.05553355491992011,
          0.05553355491992011,
          0.0
        ],
        0,
        [
          4,
          4
        ]
      ],
      [
        "Horn_ffd2_1",
        [
          0.07404473989322681,
          0.05553355491992011,
          0.0
        ],
        0,
        [
          4,
          5
        ]
      ]
    ]
  ],
  "array_dimension": [
    0.07404473989322681,
    0.09255592486653351,
    0.018511184973306703,
    0.018511184973306703
  ],
  "lattice_vector": [
    0.0,
    0.018511184973306703,
    0.0,
    0.018511184973306703,
    0.0,
    0.0
  ]
}